{
  "rows": [
    {
      "slug": "docs/security-and-privacy/data-handling-and-classification",
      "wordCount": 639,
      "emDashes": 0,
      "emPer300": 0,
      "vocabHits": 5,
      "vocabSeen": [
        "robust",
        "comprehensive",
        "multi-layered",
        "ensuring that"
      ],
      "stockHits": 0,
      "closingHits": 0,
      "closingSeen": [],
      "transitionStacks": 0,
      "boldColonBullets": 4,
      "sentenceLenStddev": 41.8,
      "signal": 5
    },
    {
      "slug": "docs/how-to-use-promptless/deep-analysis",
      "wordCount": 460,
      "emDashes": 8,
      "emPer300": 5.22,
      "vocabHits": 2,
      "vocabSeen": [
        "comprehensive"
      ],
      "stockHits": 0,
      "closingHits": 0,
      "closingSeen": [],
      "transitionStacks": 0,
      "boldColonBullets": 0,
      "sentenceLenStddev": 9.9,
      "signal": 4
    },
    {
      "slug": "docs/security-and-privacy/single-sign-on-sso-setup",
      "wordCount": 464,
      "emDashes": 0,
      "emPer300": 0,
      "vocabHits": 3,
      "vocabSeen": [
        "leverage",
        "seamless",
        "comprehensive"
      ],
      "stockHits": 0,
      "closingHits": 0,
      "closingSeen": [],
      "transitionStacks": 0,
      "boldColonBullets": 11,
      "sentenceLenStddev": 106.4,
      "signal": 4
    },
    {
      "slug": "docs/configuring-promptless/doc-collections/git-hub-repos-docs-as-code",
      "wordCount": 708,
      "emDashes": 5,
      "emPer300": 2.12,
      "vocabHits": 1,
      "vocabSeen": [
        "seamlessly"
      ],
      "stockHits": 0,
      "closingHits": 0,
      "closingSeen": [],
      "transitionStacks": 0,
      "boldColonBullets": 3,
      "sentenceLenStddev": 23.2,
      "signal": 3
    },
    {
      "slug": "docs/integrations/github-enterprise-integration",
      "wordCount": 749,
      "emDashes": 0,
      "emPer300": 0,
      "vocabHits": 2,
      "vocabSeen": [
        "navigate"
      ],
      "stockHits": 0,
      "closingHits": 0,
      "closingSeen": [],
      "transitionStacks": 0,
      "boldColonBullets": 9,
      "sentenceLenStddev": 67.7,
      "signal": 3
    },
    {
      "slug": "docs/self-hosting",
      "wordCount": 564,
      "emDashes": 0,
      "emPer300": 0,
      "vocabHits": 2,
      "vocabSeen": [
        "comprehensive"
      ],
      "stockHits": 0,
      "closingHits": 0,
      "closingSeen": [],
      "transitionStacks": 0,
      "boldColonBullets": 31,
      "sentenceLenStddev": 73.8,
      "signal": 3
    },
    {
      "slug": "docs/configuring-promptless/context-sources/confluence",
      "wordCount": 269,
      "emDashes": 2,
      "emPer300": 2.23,
      "vocabHits": 0,
      "vocabSeen": [],
      "stockHits": 0,
      "closingHits": 0,
      "closingSeen": [],
      "transitionStacks": 0,
      "boldColonBullets": 4,
      "sentenceLenStddev": 21.6,
      "signal": 2
    },
    {
      "slug": "docs/configuring-promptless/context-sources/linear",
      "wordCount": 249,
      "emDashes": 2,
      "emPer300": 2.41,
      "vocabHits": 0,
      "vocabSeen": [],
      "stockHits": 0,
      "closingHits": 0,
      "closingSeen": [],
      "transitionStacks": 0,
      "boldColonBullets": 3,
      "sentenceLenStddev": 20,
      "signal": 2
    },
    {
      "slug": "docs/configuring-promptless/triggers/api-triggers",
      "wordCount": 487,
      "emDashes": 2,
      "emPer300": 1.23,
      "vocabHits": 2,
      "vocabSeen": [
        "navigate"
      ],
      "stockHits": 0,
      "closingHits": 0,
      "closingSeen": [],
      "transitionStacks": 0,
      "boldColonBullets": 3,
      "sentenceLenStddev": 19.9,
      "signal": 2
    },
    {
      "slug": "docs/getting-started/getting-help",
      "wordCount": 156,
      "emDashes": 4,
      "emPer300": 7.69,
      "vocabHits": 0,
      "vocabSeen": [],
      "stockHits": 0,
      "closingHits": 0,
      "closingSeen": [],
      "transitionStacks": 0,
      "boldColonBullets": 0,
      "sentenceLenStddev": 10.1,
      "signal": 2
    },
    {
      "slug": "docs/getting-started/promptless-oss",
      "wordCount": 402,
      "emDashes": 3,
      "emPer300": 2.24,
      "vocabHits": 0,
      "vocabSeen": [],
      "stockHits": 0,
      "closingHits": 0,
      "closingSeen": [],
      "transitionStacks": 0,
      "boldColonBullets": 0,
      "sentenceLenStddev": 8,
      "signal": 2
    },
    {
      "slug": "docs/how-to-use-promptless/agent-knowledge-base",
      "wordCount": 306,
      "emDashes": 3,
      "emPer300": 2.94,
      "vocabHits": 0,
      "vocabSeen": [],
      "stockHits": 0,
      "closingHits": 0,
      "closingSeen": [],
      "transitionStacks": 0,
      "boldColonBullets": 0,
      "sentenceLenStddev": 8.9,
      "signal": 2
    },
    {
      "slug": "docs/how-to-use-promptless/using-the-web-interface",
      "wordCount": 553,
      "emDashes": 4,
      "emPer300": 2.17,
      "vocabHits": 0,
      "vocabSeen": [],
      "stockHits": 0,
      "closingHits": 0,
      "closingSeen": [],
      "transitionStacks": 0,
      "boldColonBullets": 4,
      "sentenceLenStddev": 10.6,
      "signal": 2
    },
    {
      "slug": "docs/integrations/bitbucket-integration",
      "wordCount": 494,
      "emDashes": 0,
      "emPer300": 0,
      "vocabHits": 1,
      "vocabSeen": [
        "navigate"
      ],
      "stockHits": 0,
      "closingHits": 0,
      "closingSeen": [],
      "transitionStacks": 0,
      "boldColonBullets": 9,
      "sentenceLenStddev": 17.2,
      "signal": 2
    },
    {
      "slug": "docs/integrations/microsoft-teams-integration",
      "wordCount": 278,
      "emDashes": 0,
      "emPer300": 0,
      "vocabHits": 2,
      "vocabSeen": [
        "navigate",
        "ensure that"
      ],
      "stockHits": 0,
      "closingHits": 0,
      "closingSeen": [],
      "transitionStacks": 0,
      "boldColonBullets": 1,
      "sentenceLenStddev": 16.7,
      "signal": 2
    },
    {
      "slug": "docs/integrations/slack-integration",
      "wordCount": 527,
      "emDashes": 5,
      "emPer300": 2.85,
      "vocabHits": 0,
      "vocabSeen": [],
      "stockHits": 0,
      "closingHits": 0,
      "closingSeen": [],
      "transitionStacks": 0,
      "boldColonBullets": 2,
      "sentenceLenStddev": 18.4,
      "signal": 2
    },
    {
      "slug": "docs/security-and-privacy/network-architecture",
      "wordCount": 293,
      "emDashes": 0,
      "emPer300": 0,
      "vocabHits": 2,
      "vocabSeen": [
        "comprehensive",
        "ensure that"
      ],
      "stockHits": 0,
      "closingHits": 0,
      "closingSeen": [],
      "transitionStacks": 0,
      "boldColonBullets": 0,
      "sentenceLenStddev": 33.1,
      "signal": 2
    },
    {
      "slug": "docs/configuring-promptless/context-sources",
      "wordCount": 370,
      "emDashes": 0,
      "emPer300": 0,
      "vocabHits": 1,
      "vocabSeen": [
        "comprehensive"
      ],
      "stockHits": 0,
      "closingHits": 0,
      "closingSeen": [],
      "transitionStacks": 0,
      "boldColonBullets": 0,
      "sentenceLenStddev": 12.7,
      "signal": 1
    },
    {
      "slug": "docs/configuring-promptless/customizing-notifications",
      "wordCount": 292,
      "emDashes": 1,
      "emPer300": 1.03,
      "vocabHits": 0,
      "vocabSeen": [],
      "stockHits": 0,
      "closingHits": 0,
      "closingSeen": [],
      "transitionStacks": 0,
      "boldColonBullets": 6,
      "sentenceLenStddev": 23.5,
      "signal": 1
    },
    {
      "slug": "docs/configuring-promptless/triggers/git-hub-commits",
      "wordCount": 644,
      "emDashes": 0,
      "emPer300": 0,
      "vocabHits": 0,
      "vocabSeen": [],
      "stockHits": 0,
      "closingHits": 0,
      "closingSeen": [],
      "transitionStacks": 0,
      "boldColonBullets": 10,
      "sentenceLenStddev": 26.6,
      "signal": 1
    },
    {
      "slug": "docs/configuring-promptless/triggers/slack-messages",
      "wordCount": 627,
      "emDashes": 1,
      "emPer300": 0.48,
      "vocabHits": 1,
      "vocabSeen": [
        "comprehensive"
      ],
      "stockHits": 0,
      "closingHits": 0,
      "closingSeen": [],
      "transitionStacks": 0,
      "boldColonBullets": 1,
      "sentenceLenStddev": 12,
      "signal": 1
    },
    {
      "slug": "docs/frequently-asked-questions/recommended-docs-providers",
      "wordCount": 206,
      "emDashes": 0,
      "emPer300": 0,
      "vocabHits": 0,
      "vocabSeen": [],
      "stockHits": 0,
      "closingHits": 0,
      "closingSeen": [],
      "transitionStacks": 0,
      "boldColonBullets": 6,
      "sentenceLenStddev": 39.3,
      "signal": 1
    },
    {
      "slug": "docs/getting-started/setup-quickstart",
      "wordCount": 265,
      "emDashes": 1,
      "emPer300": 1.13,
      "vocabHits": 0,
      "vocabSeen": [],
      "stockHits": 0,
      "closingHits": 0,
      "closingSeen": [],
      "transitionStacks": 0,
      "boldColonBullets": 8,
      "sentenceLenStddev": 17.1,
      "signal": 1
    },
    {
      "slug": "docs/integrations/github-integration",
      "wordCount": 490,
      "emDashes": 0,
      "emPer300": 0,
      "vocabHits": 1,
      "vocabSeen": [
        "navigate"
      ],
      "stockHits": 0,
      "closingHits": 0,
      "closingSeen": [],
      "transitionStacks": 0,
      "boldColonBullets": 4,
      "sentenceLenStddev": 13.4,
      "signal": 1
    },
    {
      "slug": "docs/security-and-privacy/privacy-policy",
      "wordCount": 120,
      "emDashes": 0,
      "emPer300": 0,
      "vocabHits": 1,
      "vocabSeen": [
        "comprehensive"
      ],
      "stockHits": 0,
      "closingHits": 0,
      "closingSeen": [],
      "transitionStacks": 0,
      "boldColonBullets": 0,
      "sentenceLenStddev": 34,
      "signal": 1
    },
    {
      "slug": "docs/self-hosting/kubernetes-helm",
      "wordCount": 471,
      "emDashes": 1,
      "emPer300": 0.64,
      "vocabHits": 0,
      "vocabSeen": [],
      "stockHits": 0,
      "closingHits": 0,
      "closingSeen": [],
      "transitionStacks": 0,
      "boldColonBullets": 22,
      "sentenceLenStddev": 49.2,
      "signal": 1
    },
    {
      "slug": "docs/account-management/account-management",
      "wordCount": 358,
      "emDashes": 0,
      "emPer300": 0,
      "vocabHits": 0,
      "vocabSeen": [],
      "stockHits": 0,
      "closingHits": 0,
      "closingSeen": [],
      "transitionStacks": 0,
      "boldColonBullets": 4,
      "sentenceLenStddev": 16.1,
      "signal": 0
    },
    {
      "slug": "docs/configuring-promptless/context-sources/jira",
      "wordCount": 305,
      "emDashes": 2,
      "emPer300": 1.97,
      "vocabHits": 0,
      "vocabSeen": [],
      "stockHits": 0,
      "closingHits": 0,
      "closingSeen": [],
      "transitionStacks": 0,
      "boldColonBullets": 3,
      "sentenceLenStddev": 20.8,
      "signal": 0
    },
    {
      "slug": "docs/configuring-promptless/context-sources/notion",
      "wordCount": 509,
      "emDashes": 2,
      "emPer300": 1.18,
      "vocabHits": 0,
      "vocabSeen": [],
      "stockHits": 0,
      "closingHits": 0,
      "closingSeen": [],
      "transitionStacks": 0,
      "boldColonBullets": 4,
      "sentenceLenStddev": 17,
      "signal": 0
    },
    {
      "slug": "docs/configuring-promptless/doc-collections/doc-detective-integration",
      "wordCount": 467,
      "emDashes": 0,
      "emPer300": 0,
      "vocabHits": 0,
      "vocabSeen": [],
      "stockHits": 0,
      "closingHits": 0,
      "closingSeen": [],
      "transitionStacks": 0,
      "boldColonBullets": 0,
      "sentenceLenStddev": 16.9,
      "signal": 0
    },
    {
      "slug": "docs/configuring-promptless/doc-collections/how-promptless-learns-your-docs",
      "wordCount": 436,
      "emDashes": 0,
      "emPer300": 0,
      "vocabHits": 0,
      "vocabSeen": [],
      "stockHits": 0,
      "closingHits": 0,
      "closingSeen": [],
      "transitionStacks": 0,
      "boldColonBullets": 0,
      "sentenceLenStddev": 19,
      "signal": 0
    },
    {
      "slug": "docs/configuring-promptless/triggers/git-hub-issues",
      "wordCount": 227,
      "emDashes": 0,
      "emPer300": 0,
      "vocabHits": 0,
      "vocabSeen": [],
      "stockHits": 0,
      "closingHits": 0,
      "closingSeen": [],
      "transitionStacks": 0,
      "boldColonBullets": 3,
      "sentenceLenStddev": 22.8,
      "signal": 0
    },
    {
      "slug": "docs/configuring-promptless/triggers/git-hub-p-rs",
      "wordCount": 973,
      "emDashes": 2,
      "emPer300": 0.62,
      "vocabHits": 0,
      "vocabSeen": [],
      "stockHits": 0,
      "closingHits": 0,
      "closingSeen": [],
      "transitionStacks": 0,
      "boldColonBullets": 0,
      "sentenceLenStddev": 20.9,
      "signal": 0
    },
    {
      "slug": "docs/configuring-promptless/triggers/intercom-tickets-beta",
      "wordCount": 197,
      "emDashes": 0,
      "emPer300": 0,
      "vocabHits": 0,
      "vocabSeen": [],
      "stockHits": 0,
      "closingHits": 0,
      "closingSeen": [],
      "transitionStacks": 0,
      "boldColonBullets": 4,
      "sentenceLenStddev": 18.4,
      "signal": 0
    },
    {
      "slug": "docs/configuring-promptless/triggers/microsoft-teams-messages",
      "wordCount": 219,
      "emDashes": 0,
      "emPer300": 0,
      "vocabHits": 0,
      "vocabSeen": [],
      "stockHits": 0,
      "closingHits": 0,
      "closingSeen": [],
      "transitionStacks": 0,
      "boldColonBullets": 0,
      "sentenceLenStddev": 7.2,
      "signal": 0
    },
    {
      "slug": "docs/configuring-promptless/triggers",
      "wordCount": 268,
      "emDashes": 0,
      "emPer300": 0,
      "vocabHits": 0,
      "vocabSeen": [],
      "stockHits": 0,
      "closingHits": 0,
      "closingSeen": [],
      "transitionStacks": 0,
      "boldColonBullets": 0,
      "sentenceLenStddev": 12.7,
      "signal": 0
    },
    {
      "slug": "docs/frequently-asked-questions/frequently-asked-questions",
      "wordCount": 319,
      "emDashes": 1,
      "emPer300": 0.94,
      "vocabHits": 0,
      "vocabSeen": [],
      "stockHits": 0,
      "closingHits": 0,
      "closingSeen": [],
      "transitionStacks": 0,
      "boldColonBullets": 3,
      "sentenceLenStddev": 13,
      "signal": 0
    },
    {
      "slug": "docs/getting-started/core-concepts",
      "wordCount": 322,
      "emDashes": 0,
      "emPer300": 0,
      "vocabHits": 0,
      "vocabSeen": [],
      "stockHits": 0,
      "closingHits": 0,
      "closingSeen": [],
      "transitionStacks": 0,
      "boldColonBullets": 4,
      "sentenceLenStddev": 9.1,
      "signal": 0
    },
    {
      "slug": "docs/getting-started/pilot-overview",
      "wordCount": 690,
      "emDashes": 3,
      "emPer300": 1.3,
      "vocabHits": 0,
      "vocabSeen": [],
      "stockHits": 0,
      "closingHits": 0,
      "closingSeen": [],
      "transitionStacks": 0,
      "boldColonBullets": 0,
      "sentenceLenStddev": 13,
      "signal": 0
    },
    {
      "slug": "docs/getting-started/promptless-1-0",
      "wordCount": 628,
      "emDashes": 3,
      "emPer300": 1.43,
      "vocabHits": 0,
      "vocabSeen": [],
      "stockHits": 0,
      "closingHits": 0,
      "closingSeen": [],
      "transitionStacks": 0,
      "boldColonBullets": 0,
      "sentenceLenStddev": 8.5,
      "signal": 0
    },
    {
      "slug": "docs/getting-started/welcome",
      "wordCount": 112,
      "emDashes": 0,
      "emPer300": 0,
      "vocabHits": 0,
      "vocabSeen": [],
      "stockHits": 0,
      "closingHits": 0,
      "closingSeen": [],
      "transitionStacks": 0,
      "boldColonBullets": 0,
      "sentenceLenStddev": 18.1,
      "signal": 0
    },
    {
      "slug": "docs/how-to-use-promptless/interacting-with-promptless-p-rs",
      "wordCount": 381,
      "emDashes": 1,
      "emPer300": 0.79,
      "vocabHits": 0,
      "vocabSeen": [],
      "stockHits": 0,
      "closingHits": 0,
      "closingSeen": [],
      "transitionStacks": 0,
      "boldColonBullets": 3,
      "sentenceLenStddev": 13.7,
      "signal": 0
    },
    {
      "slug": "docs/how-to-use-promptless/managing-environment-variables",
      "wordCount": 219,
      "emDashes": 0,
      "emPer300": 0,
      "vocabHits": 0,
      "vocabSeen": [],
      "stockHits": 0,
      "closingHits": 0,
      "closingSeen": [],
      "transitionStacks": 0,
      "boldColonBullets": 0,
      "sentenceLenStddev": 15.1,
      "signal": 0
    },
    {
      "slug": "docs/how-to-use-promptless/providing-feedback",
      "wordCount": 497,
      "emDashes": 2,
      "emPer300": 1.21,
      "vocabHits": 0,
      "vocabSeen": [],
      "stockHits": 0,
      "closingHits": 0,
      "closingSeen": [],
      "transitionStacks": 0,
      "boldColonBullets": 2,
      "sentenceLenStddev": 12.3,
      "signal": 0
    },
    {
      "slug": "docs/how-to-use-promptless/using-promptless-capture",
      "wordCount": 307,
      "emDashes": 1,
      "emPer300": 0.98,
      "vocabHits": 0,
      "vocabSeen": [],
      "stockHits": 0,
      "closingHits": 0,
      "closingSeen": [],
      "transitionStacks": 0,
      "boldColonBullets": 0,
      "sentenceLenStddev": 29.4,
      "signal": 0
    },
    {
      "slug": "docs/how-to-use-promptless/working-with-slack",
      "wordCount": 506,
      "emDashes": 2,
      "emPer300": 1.19,
      "vocabHits": 0,
      "vocabSeen": [],
      "stockHits": 0,
      "closingHits": 0,
      "closingSeen": [],
      "transitionStacks": 0,
      "boldColonBullets": 2,
      "sentenceLenStddev": 9.3,
      "signal": 0
    },
    {
      "slug": "docs/how-to-use-promptless",
      "wordCount": 53,
      "emDashes": 0,
      "emPer300": 0,
      "vocabHits": 0,
      "vocabSeen": [],
      "stockHits": 0,
      "closingHits": 0,
      "closingSeen": [],
      "transitionStacks": 0,
      "boldColonBullets": 0,
      "sentenceLenStddev": 11.1,
      "signal": 0
    },
    {
      "slug": "docs/integrations/atlassian-integration",
      "wordCount": 513,
      "emDashes": 0,
      "emPer300": 0,
      "vocabHits": 0,
      "vocabSeen": [],
      "stockHits": 0,
      "closingHits": 0,
      "closingSeen": [],
      "transitionStacks": 0,
      "boldColonBullets": 2,
      "sentenceLenStddev": 26,
      "signal": 0
    },
    {
      "slug": "docs/integrations/intercom-integration-beta",
      "wordCount": 117,
      "emDashes": 0,
      "emPer300": 0,
      "vocabHits": 0,
      "vocabSeen": [],
      "stockHits": 0,
      "closingHits": 0,
      "closingSeen": [],
      "transitionStacks": 0,
      "boldColonBullets": 0,
      "sentenceLenStddev": 19.5,
      "signal": 0
    },
    {
      "slug": "docs/integrations/launchdarkly-integration-beta",
      "wordCount": 246,
      "emDashes": 0,
      "emPer300": 0,
      "vocabHits": 0,
      "vocabSeen": [],
      "stockHits": 0,
      "closingHits": 0,
      "closingSeen": [],
      "transitionStacks": 0,
      "boldColonBullets": 0,
      "sentenceLenStddev": 11.6,
      "signal": 0
    },
    {
      "slug": "docs/integrations/linear-integration",
      "wordCount": 169,
      "emDashes": 0,
      "emPer300": 0,
      "vocabHits": 0,
      "vocabSeen": [],
      "stockHits": 0,
      "closingHits": 0,
      "closingSeen": [],
      "transitionStacks": 0,
      "boldColonBullets": 0,
      "sentenceLenStddev": 16.3,
      "signal": 0
    },
    {
      "slug": "docs/integrations",
      "wordCount": 389,
      "emDashes": 0,
      "emPer300": 0,
      "vocabHits": 0,
      "vocabSeen": [],
      "stockHits": 0,
      "closingHits": 0,
      "closingSeen": [],
      "transitionStacks": 0,
      "boldColonBullets": 0,
      "sentenceLenStddev": 43.1,
      "signal": 0
    },
    {
      "slug": "docs/security-and-privacy/compliance-and-certifications",
      "wordCount": 350,
      "emDashes": 0,
      "emPer300": 0,
      "vocabHits": 0,
      "vocabSeen": [],
      "stockHits": 0,
      "closingHits": 0,
      "closingSeen": [],
      "transitionStacks": 0,
      "boldColonBullets": 5,
      "sentenceLenStddev": 17.3,
      "signal": 0
    },
    {
      "slug": "docs/security-and-privacy/promptless-subprocessors",
      "wordCount": 341,
      "emDashes": 0,
      "emPer300": 0,
      "vocabHits": 0,
      "vocabSeen": [],
      "stockHits": 0,
      "closingHits": 0,
      "closingSeen": [],
      "transitionStacks": 0,
      "boldColonBullets": 3,
      "sentenceLenStddev": 31.8,
      "signal": 0
    },
    {
      "slug": "docs/security-and-privacy",
      "wordCount": 136,
      "emDashes": 0,
      "emPer300": 0,
      "vocabHits": 0,
      "vocabSeen": [],
      "stockHits": 0,
      "closingHits": 0,
      "closingSeen": [],
      "transitionStacks": 0,
      "boldColonBullets": 0,
      "sentenceLenStddev": 31.8,
      "signal": 0
    }
  ],
  "totals": {
    "highSignal": 3,
    "modSignal": 3,
    "lowSignal": 49,
    "emHeavy": 9,
    "closingHits": 0,
    "boldColonHeavy": 9
  }
}